checkuser/__init__.py
checkuser/__main__.py
checkuser/checker.py
checkuser/daemon.py
checkuser/server.py
checkuser/utils.py
checkuser/worker.py
CheckerUser-2.2.13.dist-info/LICENSE
CheckerUser-2.2.13.dist-info/METADATA
CheckerUser-2.2.13.dist-info/WHEEL
CheckerUser-2.2.13.dist-info/entry_points.txt
CheckerUser-2.2.13.dist-info/top_level.txt
CheckerUser-2.2.13.dist-info/RECORD
