Metadata-Version: 2.1
Name: CheckerUser
Version: 2.2.13
Home-page: https://github.com/DuTra01/CheckUser
Author: Glemison C. Dutra
Author-email: glemyson20@gmail.com
License: MIT
License-File: LICENSE
